llmailbot/__init__.py
llmailbot/__main__.py
llmailbot/config.py
llmailbot/core.py
llmailbot/dkim.py
llmailbot/duration.py
llmailbot/email/__init__.py
llmailbot/email/fetch.py
llmailbot/email/model.py
llmailbot/email/send.py
llmailbot/enums.py
llmailbot/logging.py
llmailbot/mailbot.py
llmailbot/queue/__init__.py
llmailbot/queue/core.py
llmailbot/queue/memory.py
llmailbot/queue/redis.py
llmailbot/ratelimit.py
llmailbot/security.py
llmailbot/taskrun.py
llmailbot-0.4.3.dist-info/LICENSE
llmailbot-0.4.3.dist-info/METADATA
llmailbot-0.4.3.dist-info/WHEEL
llmailbot-0.4.3.dist-info/entry_points.txt
llmailbot-0.4.3.dist-info/RECORD
